i3egg/__init__.py
i3egg/egg.py
test/__init__.py
test/test_egg.py
i3egg-0.9.3.dist-info/LICENSE
i3egg-0.9.3.dist-info/METADATA
i3egg-0.9.3.dist-info/WHEEL
i3egg-0.9.3.dist-info/entry_points.txt
i3egg-0.9.3.dist-info/top_level.txt
i3egg-0.9.3.dist-info/zip-safe
i3egg-0.9.3.dist-info/RECORD
