Metadata-Version: 2.1
Name: i3egg
Version: 0.9.3
Summary: An overly simple timer for i3.
Home-page: https://github.com/vaneseltine/i3egg
Author: Matt VanEseltine
Author-email: matvan@umich.edu
License: AGPL-3.0-or-later
Project-URL: Issue Tracker, https://github.com/vaneseltine/i3egg/issues
Keywords: i3,i3wm
Platform: UNKNOWN
Classifier: Development Status :: 4 - Beta
Classifier: Environment :: Other Environment
Classifier: Intended Audience :: End Users/Desktop
Classifier: License :: OSI Approved :: GNU Affero General Public License v3 or later (AGPLv3+)
Classifier: Natural Language :: English
Classifier: Operating System :: POSIX :: Linux
Classifier: Programming Language :: Python
Classifier: Programming Language :: Python :: 3.6
Classifier: Programming Language :: Python :: 3.7
Classifier: Programming Language :: Python :: 3.8
Classifier: Programming Language :: Python :: 3.9
Classifier: Programming Language :: Python :: 3 :: Only
Classifier: Topic :: Utilities
Classifier: Typing :: Typed
